django_litestream/__about__.py
django_litestream/__init__.py
django_litestream/apps.py
django_litestream/conf.py
django_litestream/management/__init__.py
django_litestream/management/commands/__init__.py
django_litestream/management/commands/litestream.py
django_litestream-0.3.1.dist-info/METADATA
django_litestream-0.3.1.dist-info/WHEEL
django_litestream-0.3.1.dist-info/licenses/LICENSE.txt
django_litestream-0.3.1.dist-info/RECORD
