Metadata-Version: 2.4
Name: django-litestream
Version: 0.3.1
Summary: Django integration with litestream, a a standalone streaming replication tool for SQLite.
Project-URL: Documentation, https://github.com/Tobi-De/django-litestream#readme
Project-URL: Issues, https://github.com/Tobi-De/django-litestream/issues
Project-URL: Source, https://github.com/Tobi-De/django-litestream
Author-email: Tobi DEGNON <tobidegnon@proton.me>
License: MIT License
License-File: LICENSE.txt
Keywords: backup,django,litestream,replication,sqlite,sqlite3
Classifier: Development Status :: 4 - Beta
Classifier: Framework :: Django :: 4.2
Classifier: Framework :: Django :: 5.0
Classifier: Framework :: Django :: 5.1
Classifier: Intended Audience :: Developers
Classifier: License :: OSI Approved :: MIT License
Classifier: Natural Language :: English
Classifier: Programming Language :: Python
Classifier: Programming Language :: Python :: 3 :: Only
Classifier: Programming Language :: Python :: 3.8
Classifier: Programming Language :: Python :: 3.9
Classifier: Programming Language :: Python :: 3.10
Classifier: Programming Language :: Python :: 3.11
Classifier: Programming Language :: Python :: 3.12
Classifier: Programming Language :: Python :: Implementation :: CPython
Classifier: Programming Language :: Python :: Implementation :: PyPy
Requires-Python: >=3.8
Requires-Dist: django>=4.2
Requires-Dist: litestream-bin
Requires-Dist: pyyaml
Requires-Dist: rich
